tatter/KL_estimator.py
tatter/TST_estimators.py
tatter/__init__.py
tatter/posterior_predictive_check.py
tatter/test_module.py
tatter/tests/__init__.py
tatter/tests/cluster_catalog_comp.py
tatter/tests/gaussian_vs_lognormal.py
tatter/tests/mnist_test.py
tatter-1.0.0.dist-info/LICENSE
tatter-1.0.0.dist-info/METADATA
tatter-1.0.0.dist-info/WHEEL
tatter-1.0.0.dist-info/top_level.txt
tatter-1.0.0.dist-info/RECORD
