Metadata-Version: 2.1
Name: tatter
Version: 1.0.0
Summary: Two-Sample Hypothesis Test. A hypothesis testing tool for multi-dimensional data.
Home-page: https://github.com/afarahi/tatter
Author: Arya Farahi
Author-email: arya.farahi@austin.utexas.edu
License: MIT
Keywords: MMD,Two-sample test,K-S,K-L
Platform: UNKNOWN
Classifier: Programming Language :: Python :: 3
Classifier: Programming Language :: Python :: 3.6
Classifier: Programming Language :: Python :: 3.7
Classifier: Programming Language :: Python :: 3.8
Classifier: Programming Language :: Python :: 3.9
Classifier: Intended Audience :: Science/Research
Classifier: License :: OSI Approved :: MIT License
Classifier: Topic :: Scientific/Engineering
Classifier: Topic :: Scientific/Engineering :: Astronomy
Classifier: Topic :: Scientific/Engineering :: Physics
Requires-Dist: numpy
Requires-Dist: matplotlib
Requires-Dist: sklearn
Requires-Dist: joblib
Requires-Dist: tqdm
Requires-Dist: pathlib
